Metadata-Version: 2.1
Name: pymapee
Version: 0.0.4
Summary: A Simple Python package to pre-processing satellite data using Google Earth Engine.
Home-page: https://github.com/tuyenhavan/pymapee
Author: Tuyen Ha
Author-email: tuyenmassey@gmail.com
License: MIT license
Keywords: pymapee
Platform: UNKNOWN
Classifier: Development Status :: 2 - Pre-Alpha
Classifier: Intended Audience :: Developers
Classifier: License :: OSI Approved :: MIT License
Classifier: Natural Language :: English
Classifier: Programming Language :: Python :: 3
Classifier: Programming Language :: Python :: 3.7
Classifier: Programming Language :: Python :: 3.8
Classifier: Programming Language :: Python :: 3.9
Classifier: Programming Language :: Python :: 3.10
Requires-Python: >=3.7
